wrapper/__init__.py
wrapper/alicebluepy.py
alice_blue_sdk_codifi-2.0.2.dist-info/LICENSE.txt
alice_blue_sdk_codifi-2.0.2.dist-info/METADATA
alice_blue_sdk_codifi-2.0.2.dist-info/WHEEL
alice_blue_sdk_codifi-2.0.2.dist-info/top_level.txt
alice_blue_sdk_codifi-2.0.2.dist-info/RECORD
